Metadata-Version: 2.1
Name: pyteomics-utils
Version: 0.0.5
Summary: Simple but handy CLI tools for everyday data analysis tasks.
Author: Lev Levitsky
Author-email: pyteomics@googlegroups.com
License: License :: OSI Approved :: Apache Software License
Platform: UNKNOWN
Classifier: Intended Audience :: Science/Research
Classifier: Programming Language :: Python :: 3
Classifier: Topic :: Education
Classifier: Topic :: Scientific/Engineering :: Bio-Informatics
Classifier: Topic :: Scientific/Engineering :: Chemistry
Classifier: Topic :: Scientific/Engineering :: Physics
Classifier: Topic :: Software Development :: Libraries
Provides-Extra: XML
License-File: LICENSE
